Metadata-Version: 1.0
Name: pyemtapi
Version: 1.0
Summary: Python library to access some functionality of the REST API of the Municipal Transport Company of Madrid.
Home-page: https://github.com/RafaMunoz/pyemtapi
Author: Rafa Munoz
Author-email: rafa93m@gmail.com
License: MIT
Keywords: api emt madrid python
Platform: UNKNOWN
